stream_zip/__init__.py
stream_zip/py.typed
stream_zip-0.0.83.dist-info/METADATA
stream_zip-0.0.83.dist-info/WHEEL
stream_zip-0.0.83.dist-info/licenses/LICENSE
stream_zip-0.0.83.dist-info/RECORD
