Metadata-Version: 2.3
Name: stream-zip
Version: 0.0.83
Summary: Python function to construct a ZIP archive with stream processing - without having to store the entire ZIP in memory or disk
Project-URL: Documentation, https://stream-zip.docs.trade.gov.uk/
Project-URL: Source, https://github.com/uktrade/stream-zip
Author-email: Department for International Trade <sre@digital.trade.gov.uk>
License-File: LICENSE
Classifier: License :: OSI Approved :: MIT License
Classifier: Programming Language :: Python :: 3
Classifier: Topic :: System :: Archiving :: Compression
Requires-Python: >=3.6.7
Requires-Dist: pycryptodome>=3.10.1
Provides-Extra: ci
Requires-Dist: mypy==0.971; extra == 'ci'
Requires-Dist: pycryptodome==3.10.1; extra == 'ci'
Requires-Dist: pyzipper==0.3.6; extra == 'ci'
Requires-Dist: stream-unzip==0.0.86; extra == 'ci'
Requires-Dist: types-contextvars==2.4.7.3; (python_version < '3.7') and extra == 'ci'
Provides-Extra: dev
Requires-Dist: coverage>=6.2; extra == 'dev'
Requires-Dist: mypy>=0.971; extra == 'dev'
Requires-Dist: pytest-cov>=3.0.0; extra == 'dev'
Requires-Dist: pytest>=7.0.1; extra == 'dev'
Requires-Dist: pyzipper>=0.3.6; extra == 'dev'
Requires-Dist: stream-unzip>=0.0.86; extra == 'dev'
Requires-Dist: types-contextvars>=2.4.7.3; (python_version < '3.7') and extra == 'dev'
